eegverse/__init__.py
eegverse/api.py
eegverse/bench/baseline_seizure_cnn.py
eegverse/bench/erp_baseline_logreg.py
eegverse/bench/mi_baseline.py
eegverse/bench/sleep_baseline_cnn.py
eegverse/datasets/chbmit.py
eegverse/datasets/openneuro_erp.py
eegverse/datasets/physionet_mi.py
eegverse/datasets/sleep_edf.py
eegverse/utils/splits.py
eegverse-0.3.0.dist-info/licenses/LICENSE
eegverse-0.3.0.dist-info/METADATA
eegverse-0.3.0.dist-info/WHEEL
eegverse-0.3.0.dist-info/top_level.txt
eegverse-0.3.0.dist-info/RECORD
