Metadata-Version: 2.4
Name: eegverse
Version: 0.3.0
Summary: EEGVERSE: A Universe of Annotated EEG Data
Author: zahransa
License: MIT License
Project-URL: Homepage, https://github.com/zahransa/eegverse
Project-URL: Repository, https://github.com/zahransa/eegverse
Project-URL: Issues, https://github.com/zahransa/eegverse/issues
Classifier: Development Status :: 3 - Alpha
Classifier: License :: OSI Approved :: MIT License
Classifier: Programming Language :: Python :: 3
Classifier: Programming Language :: Python :: 3 :: Only
Classifier: Programming Language :: Python :: 3.9
Classifier: Programming Language :: Python :: 3.10
Classifier: Programming Language :: Python :: 3.11
Classifier: Programming Language :: Python :: 3.12
Classifier: Intended Audience :: Science/Research
Classifier: Topic :: Scientific/Engineering
Classifier: Topic :: Scientific/Engineering :: Artificial Intelligence
Classifier: Topic :: Scientific/Engineering :: Information Analysis
Requires-Python: >=3.9
License-File: LICENSE
Requires-Dist: numpy
Requires-Dist: scipy
Requires-Dist: pandas
Requires-Dist: mne>=1.6
Requires-Dist: mne-bids>=0.13
Requires-Dist: scikit-learn
Requires-Dist: pooch
Provides-Extra: dl
Requires-Dist: torch; extra == "dl"
Provides-Extra: openneuro
Requires-Dist: openneuro-py; extra == "openneuro"
Provides-Extra: dev
Requires-Dist: build; extra == "dev"
Requires-Dist: twine; extra == "dev"
Requires-Dist: pytest; extra == "dev"
Dynamic: license-file
